Workbook

Sheet Instructions
B2: ROI Analysis Template
B3: A structured workbook for building the business case: capture costs and benefits, then calculate ROI, payback, NPV, and IRR.
B5: How to use this workbook
B6: 1. Assumptions — set the discount rate, currency, and analysis start date (yellow inputs) that drive the ROI Summary.
B7: 2. Cost Inputs — log every cost line item (one-time or recurring) by category, spread across Year 0-5.
B8: • Year 0 = upfront/implementation costs incurred before benefits begin.
B9: • Use Type to flag One-time vs. Recurring for easier review later.
B10: 3. Benefit Inputs — log every benefit line item (hard $ savings or soft/qualitative-adjacent value) by category, Year 0-5.
B11: • Hard benefits = quantifiable, auditable savings or revenue (e.g., FTE cost avoidance, reduced cycle time x rate).
B12: • Soft benefits = directional value you still want to track (e.g., improved NPS) — keep these separate from Hard totals if your audience only counts Hard $.
B13: 4. ROI Summary — auto-calculates from Cost Inputs and Benefit Inputs: net cash flow, cumulative cash flow, ROI %, payback period, NPV, and IRR.
B14: 5. Lists tab — edit the dropdown source lists (Cost Category, Benefit Category, Type, Owner) to match your program.
... B21: Yellow fill example:

Sheet Lists
A1: Cost Category | B1: Benefit Category | C1: Cost Type | D1: Benefit Type | E1: Confidence
A2: Labor / Implementation | B2: Labor / FTE Savings | C2: One-time | D2: Hard (quantified $) | E2: High
A3: Technology / Licensing | B3: Cost Avoidance | C3: Recurring | D3: Soft (directional / qualitative) | E3: Medium
A4: Infrastructure | B4: Revenue Growth | E4: Low
A5: Training / Change Management | B5: Cycle Time Reduction
A6: Consulting / Professional Services | B6: Error / Rework Reduction
A7: Ongoing Support / Maintenance | B7: Risk / Compliance Reduction
A8: Other | B8: Customer Experience
B9: Other

Sheet Assumptions
A1: Assumptions
A2: Key drivers for the ROI Summary calculations. Edit the yellow cells.
A4: Assumption | B4: Value | C4: Notes
A5: Analysis Name / Initiative | C5: Name of the initiative or business case
A6: Analysis Start Date | C6: Date Year 0 begins
A7: Currency | B7: USD | C7: Currency used throughout this workbook
A8: Discount Rate (Annual %) | B8: 0.1 | C8: Used for NPV and discounted payback calculations
A9: Time Horizon (Years) | B9: 5 | C9: Number of years modeled beyond Year 0
A10: Prepared By | C10: Analyst / owner of this business case

Sheet Cost Inputs
A1: Cost Inputs
A2: One row per cost line item. Year 0 = upfront/implementation costs before benefits begin.
A3: Cost ID | B3: Category | C3: Description | D3: Type | E3: Owner | F3: Confidence | G3: Year 0 | H3: Year 1 | I3: Year 2 | J3: Year 3 | K3: Year 4 | L3: Year 5 | M3: Total | N3: Notes
A4: =IF(C4="","","C-"&TEXT(ROW()-3,"000")) | M4: =SUM(G4:L4) -> 0
A5: =IF(C5="","","C-"&TEXT(ROW()-3,"000")) | M5: =SUM(G5:L5) -> 0
A6: =IF(C6="","","C-"&TEXT(ROW()-3,"000")) | M6: =SUM(G6:L6) -> 0
A7: =IF(C7="","","C-"&TEXT(ROW()-3,"000")) | M7: =SUM(G7:L7) -> 0
A8: =IF(C8="","","C-"&TEXT(ROW()-3,"000")) | M8: =SUM(G8:L8) -> 0
A9: =IF(C9="","","C-"&TEXT(ROW()-3,"000")) | M9: =SUM(G9:L9) -> 0
A10: =IF(C10="","","C-"&TEXT(ROW()-3,"000")) | M10: =SUM(G10:L10) -> 0
A11: =IF(C11="","","C-"&TEXT(ROW()-3,"000")) | M11: =SUM(G11:L11) -> 0
A12: =IF(C12="","","C-"&TEXT(ROW()-3,"000")) | M12: =SUM(G12:L12) -> 0
A13: =IF(C13="","","C-"&TEXT(ROW()-3,"000")) | M13: =SUM(G13:L13) -> 0
A14: =IF(C14="","","C-"&TEXT(ROW()-3,"000")) | M14: =SUM(G14:L14) -> 0
A15: =IF(C15="","","C-"&TEXT(ROW()-3,"000")) | M15: =SUM(G15:L15) -> 0
... A33: =IF(C33="","","C-"&TEXT(ROW()-3,"000")) | M33: =SUM(G33:L33) -> 0
B34: TOTAL COSTS | G34: =SUM(G4:G33) -> 0 | H34: =SUM(H4:H33) -> 0 | I34: =SUM(I4:I33) -> 0 | J34: =SUM(J4:J33) -> 0 | K34: =SUM(K4:K33) -> 0 | L34: =SUM(L4:L33) -> 0 | M34: =SUM(M4:M33) -> 0

Sheet Benefit Inputs
A1: Benefit Inputs
A2: One row per benefit line item. Keep Hard $ and Soft benefits distinguishable via the Type column.
A3: Benefit ID | B3: Category | C3: Description | D3: Type | E3: Owner | F3: Confidence | G3: Year 0 | H3: Year 1 | I3: Year 2 | J3: Year 3 | K3: Year 4 | L3: Year 5 | M3: Total | N3: Notes
A4: =IF(C4="","","B-"&TEXT(ROW()-3,"000")) | M4: =SUM(G4:L4) -> 0
A5: =IF(C5="","","B-"&TEXT(ROW()-3,"000")) | M5: =SUM(G5:L5) -> 0
A6: =IF(C6="","","B-"&TEXT(ROW()-3,"000")) | M6: =SUM(G6:L6) -> 0
A7: =IF(C7="","","B-"&TEXT(ROW()-3,"000")) | M7: =SUM(G7:L7) -> 0
A8: =IF(C8="","","B-"&TEXT(ROW()-3,"000")) | M8: =SUM(G8:L8) -> 0
A9: =IF(C9="","","B-"&TEXT(ROW()-3,"000")) | M9: =SUM(G9:L9) -> 0
A10: =IF(C10="","","B-"&TEXT(ROW()-3,"000")) | M10: =SUM(G10:L10) -> 0
A11: =IF(C11="","","B-"&TEXT(ROW()-3,"000")) | M11: =SUM(G11:L11) -> 0
A12: =IF(C12="","","B-"&TEXT(ROW()-3,"000")) | M12: =SUM(G12:L12) -> 0
A13: =IF(C13="","","B-"&TEXT(ROW()-3,"000")) | M13: =SUM(G13:L13) -> 0
A14: =IF(C14="","","B-"&TEXT(ROW()-3,"000")) | M14: =SUM(G14:L14) -> 0
A15: =IF(C15="","","B-"&TEXT(ROW()-3,"000")) | M15: =SUM(G15:L15) -> 0
... A33: =IF(C33="","","B-"&TEXT(ROW()-3,"000")) | M33: =SUM(G33:L33) -> 0
B34: TOTAL BENEFITS (ALL) | G34: =SUM(G4:G33) -> 0 | H34: =SUM(H4:H33) -> 0 | I34: =SUM(I4:I33) -> 0 | J34: =SUM(J4:J33) -> 0 | K34: =SUM(K4:K33) -> 0 | L34: =SUM(L4:L33) -> 0 | M34: =SUM(M4:M33) -> 0
B35: TOTAL HARD $ BENEFITS | G35: =SUMIF($D$4:$D$33,"Hard (quantified $)",G4:G33) -> 0 | H35: =SUMIF($D$4:$D$33,"Hard (quantified $)",H4:H33) -> 0 | I35: =SUMIF($D$4:$D$33,"Hard (quantified $)",I4:I33) -> 0 | J35: =SUMIF($D$4:$D$33,"Hard (quantified $)",J4:J33) -> 0 | K35: =SUMIF($D$4:$D$33,"Hard (quantified $)",K4:K33) -> 0 | L35: =SUMIF($D$4:$D$33,"Hard (quantified $)",L4:L33) -> 0 | M35: =SUMIF($D$4:$D$33,"Hard (quantified $)",M4:M33) -> 0

Sheet ROI Summary
A1: ROI Summary
A2: Auto-calculated from Cost Inputs and Benefit Inputs (Hard $ benefits only, per Assumptions discount rate).
A4: ($ unless noted) | B4: Year 0 | C4: Year 1 | D4: Year 2 | E4: Year 3 | F4: Year 4 | G4: Year 5
A5: Total Costs | B5: ='Cost Inputs'!G34 -> 0 | C5: ='Cost Inputs'!H34 -> 0 | D5: ='Cost Inputs'!I34 -> 0 | E5: ='Cost Inputs'!J34 -> 0 | F5: ='Cost Inputs'!K34 -> 0 | G5: ='Cost Inputs'!L34 -> 0
A6: Total Benefits (Hard $) | B6: ='Benefit Inputs'!G35 -> 0 | C6: ='Benefit Inputs'!H35 -> 0 | D6: ='Benefit Inputs'!I35 -> 0 | E6: ='Benefit Inputs'!J35 -> 0 | F6: ='Benefit Inputs'!K35 -> 0 | G6: ='Benefit Inputs'!L35 -> 0
A7: Net Cash Flow | B7: =B6-B5 -> 0 | C7: =C6-C5 -> 0 | D7: =D6-D5 -> 0 | E7: =E6-E5 -> 0 | F7: =F6-F5 -> 0 | G7: =G6-G5 -> 0
A8: Cumulative Cash Flow | B8: =B7 -> 0 | C8: =B8+C7 -> 0 | D8: =C8+D7 -> 0 | E8: =D8+E7 -> 0 | F8: =E8+F7 -> 0 | G8: =F8+G7 -> 0
A9: Discount Factor | B9: =1/(1+Assumptions!$B$8)^0 -> 1 | C9: =1/(1+Assumptions!$B$8)^1 -> 0.90909091 | D9: =1/(1+Assumptions!$B$8)^2 -> 0.82644628 | E9: =1/(1+Assumptions!$B$8)^3 -> 0.7513148 | F9: =1/(1+Assumptions!$B$8)^4 -> 0.68301346 | G9: =1/(1+Assumptions!$B$8)^5 -> 0.62092132
A10: Discounted Cash Flow | B10: =B7*B9 -> 0 | C10: =C7*C9 -> 0 | D10: =D7*D9 -> 0 | E10: =E7*E9 -> 0 | F10: =F7*F9 -> 0 | G10: =G7*G9 -> 0
A11: Cumulative Discounted Cash Flow | B11: =B10 -> 0 | C11: =B11+C10 -> 0 | D11: =C11+D10 -> 0 | E11: =D11+E10 -> 0 | F11: =E11+F10 -> 0 | G11: =F11+G10 -> 0
A14: Key Metrics
A15: Total Investment (Costs) | B15: =SUM(B5:G5) -> 0
A16: Total Benefit (Hard $) | B16: =SUM(B6:G6) -> 0
A17: Net Benefit | B17: =B16-B15 -> 0
A18: Simple ROI % | B18: =IF(B15=0,"-",B17/B15) -> -
A19: NPV (at Assumptions discount rate) | B19: =NPV(Assumptions!$B$8,C7:G7)+B7 -> 0
A20: IRR | B20: =IFERROR(IRR(B7:G7),"n/a") -> n/a
A21: Payback Period (years, undiscounted) | B21: =IFERROR(IF(MATCH(TRUE(),INDEX(B8:G8>=0,0),0)=1,0,(MATCH(TRUE(),INDEX(B8:G8>=0,0),0)-2)+(-INDEX(B8:G8,MATCH(TRUE(),INDEX(B8:G8>=0,0),0)-1)/INDEX(B7:G7,MATCH(TRUE(),INDEX(B8:G8>=0,0),0)))),"n/a") -> 0
A22: Discounted Payback Period (years) | B22: =IFERROR(IF(MATCH(TRUE(),INDEX(B11:G11>=0,0),0)=1,0,(MATCH(TRUE(),INDEX(B11:G11>=0,0),0)-2)+(-INDEX(B11:G11,MATCH(TRUE(),INDEX(B11:G11>=0,0),0)-1)/INDEX(B10:G10,MATCH(TRUE(),INDEX(B11:G11>=0,0),0)))),"n/a") -> 0
A24: Note: ROI metrics use Hard $ benefits only (Benefit Inputs "Hard (quantified $)" rows). Soft benefits are tracked in Benefit Inputs but excluded from NPV/IRR/ROI% for a conservative, auditable business case.
